Workbook

Sheet Costos
A1: CASA ÓGA | COSTOS Y PRESUPUESTO
A3: Concepto | B3: Costo inicial (USD) | C3: Costo anual (USD) | D3: Tipo de cifra
A4: Desarrollo y puesta a punto del modelo | B4: 3000 | C4: 0 | D4: Costo fijado por el equipo consultor
A5: Preparación e integración de datos | B5: 1000 | C5: 0 | D5: Costo fijado por el equipo consultor
A6: Limpieza de datos | B6: 800 | C6: 0 | D6: Costo fijado por el equipo consultor
A7: Capacitación de 35 usuarios | B7: 900 | C7: 0 | D7: Estimación para 35 usuarios
A8: Altas de los sistemas de ventas e inventario | B8: 3000 | C8: 0 | D8: Cotización de Casa Óga (antes de IVA)
A9: Computadora e infraestructura existente | B9: 0 | C9: 0 | D9: Disponible en Casa Óga
A10: Licencias adicionales | B10: 0 | C10: 0 | D10: Se reutilizan las licencias actuales
A11: Abonos de las exportaciones | B11: 0 | C11: 2040 | D11: USD 90 + 80 al mes, cotizado
A12: Responsable interno | B12: 0 | C12: 3120 | D12: 5 horas semanales × USD 12 × 52
A13: Apoyo externo trimestral | B13: 0 | C13: 800 | D13: Estimación de USD 200 trimestrales
A14: Contingencia: 10% de los costos iniciales | B14: =SUM(B4:B10)*0.1 -> 870
A15: TOTAL INVERSIÓN INICIAL | B15: =SUM(B4:B10)+B14 -> 9570
A16: TOTAL RECURRENTE ANUAL | C16: =SUM(C4:C13) -> 5960
A17: TOTAL AÑO 1 | B17: =B15+C16 -> 15530
A19: Referencias aprobadas | B19: USD 30.000 para inversión inicial | C19: USD 6.000 por año | D19: Los costos estimados deberán confirmarse
A20: Impuestos | B20: Las altas cotizadas no incluyen IVA | D20: Sumar si el IVA no puede recuperarse
A21: Criterio de actualización | B21: Los tres importes indicados por el equipo consultor | C21: Se conservan las cotizaciones de proveedores | D21: Mantenimiento sin cambios
A22: Nota de lectura | B22: La preparación de datos no reemplaza las altas de los sistemas | D22: Se presupuestan como trabajos distintos
A23: IVA | B23: El costo de alta de proveedores excluye IVA | D23: No incluido en esta proyección

Sheet Supuestos
A1: CASA ÓGA | SUPUESTOS DEL CÁLCULO
A3: Supuesto | B3: Valor | C3: Justificación
A4: Capital inmovilizado observado, ARS | B4: 83900000 | C4: Diciembre de 2025
A5: Posiciones inmovilizadas | B5: 661 | C5: Diciembre de 2025
A6: Pesos por USD | B6: 1560 | C6: Tipo de cambio de referencia, 26/10/2026
A7: Costo mensual de inmovilización | B7: 0.05 | C7: Confirmado por la empresa, sobre el costo
A8: Meses que se espera ahorrar | B8: 3 | C8: Horizonte de predicción; hipótesis de evaluación
A9: Porcentaje vendido en liquidación temprana | B9: 0.85 | C9: Experiencia comercial informada
A10: Precio de liquidación temprana / lista | B10: 0.825 | C10: Punto medio de 75%-90%
A11: Porcentaje vendido en cierre tardío | B11: 0.7 | C11: Experiencia comercial informada
A12: Precio de cierre tardío / lista | B12: 0.55 | C12: Punto medio de 50%-60%
A13: Margen de lista | B13: 0.45 | C13: Referencia comercial para aproximar precio de lista
A14: Proporción que terminaría en cierre tardío | B14: 0.25 | C14: Supuesto conservador, pendiente de validar
A15: Acciones efectivas (recuperan valor) | B15: 0.6 | C15: Referencia al 60% de ventas posteriores a transferencia
... A22: Tiempo manual que se ahorra | B22: 0.7 | C22: Supuesto base, por verificar
A24: CÁLCULOS REPRODUCIBLES | B24: Importe | C24: Fórmula o explicación
A25: Capital promedio por posición, USD | B25: =B4/B5/B6 -> 81.364677 | C25: ARS 83,9 millones / 661 / tipo de cambio
A26: Mejora posible por anticipar liquidación, USD | B26: =B25*(B9*B10-B11*B12)/(1-B13) -> 46.784689 | C26: Diferencia de precio y unidades vendidas
A27: Ahorro por 3 meses de inmovilización, USD | B27: =B25*B7*B8 -> 12.204702 | C27: 5% del costo por cada mes ahorrado
A28: Beneficio medio por acción correcta, USD | B28: =B15*(B27+B26*B14) -> 14.340524 | C28: Éxito del 60%; 25% de casos evita cierre tardío
A29: Costo evitado por una falsa acción, USD | B29: =B16/B6 -> 3.1410256 | C29: Se supone una unidad por posición; revisar en piloto
A30: Aciertos incrementales estimados por año | B30: =B19*12/B20 -> 274 | C30: Extrapolación de seis meses
A31: Ahorro del trabajo manual por año, USD | B31: =B17*B18*B22 -> 4032 | C31: Solo equivale a efectivo si evita costos reales
A32: Beneficio predictivo incremental, USD | B32: =B30*B21*(B28+B29) -> 3352.9613 | C32: Se actúa sobre 70% de alertas
A33: Beneficio anual total, USD | B33: =B31+B32 -> 7384.9613 | C33: Beneficio del ranking + horas ahorradas
A34: Costo año 1, USD | B34: =Costos!B17 -> 15530 | C34: Costo inicial más anual
A35: Retorno año 1 | B35: =(B33-B34)/B34 -> -0.52447126 | C35: Expresado como porcentaje
A36: Recupero simple, meses | B36: =B34/B33*12 -> 25.235068 | C36: Método indicado en la consigna
A37: Recupero con costos recurrentes, meses | B37: =IF(B33>Costos!C16,Costos!B15/(B33-Costos!C16)*12,"No recupera") -> 80.591664 | C37: Más realista para varios años
A39: EVALUACIÓN PLURIANUAL Y CONDICIONES | B39: Importe | C39: Explicación
A40: Costos acumulados a 3 años | B40: =Costos!B15+Costos!C16*3 -> 27450 | C40: Inversión inicial y tres años de gastos
A41: ROI esperado a 3 años | B41: =(3*B33-B40)/B40 -> -0.19290041 | C41: Tres años de beneficios y costos acumulados
A42: Beneficio anual necesario para cubrir 3 años | B42: =Costos!C16+Costos!B15/3 -> 9150 | C42: Umbral para ROI de tres años igual a cero
A43: Beneficio anual para recuperar en 12 meses | B43: =Costos!B17 -> 15530 | C43: Cubre todos los gastos del primer año
A44: Beneficio anual para recuperar en 24 meses, con mantenimiento | B44: =Costos!C16+Costos!B15/2 -> 10745 | C44: Inversión inicial amortizada en dos años
A45: Diferencia anual para ser viable a tres años | B45: =B42-B33 -> 1765.0387 | C45: Aumento sobre beneficio esperado
A46: Aumento porcentual requerido a tres años | B46: =B45/B33 -> 0.23900447 | C46: Supuesto más sensible del proyecto

Sheet Escenarios
A1: CASA ÓGA | ESCENARIOS ANUALES
A3: Escenario | B3: Adopción | C3: Acción exitosa | D3: Terminaban en cierre | E3: Horas ahorradas | F3: Valor por acierto (USD) | G3: Beneficio predictivo (USD) | H3: Valor de horas ahorradas | I3: Beneficio anual | J3: ROI año 1 | K3: Recupero simple (meses)
A4: Conservador | B4: 0.6 | C4: 0.5 | D4: 0.15 | E4: 0.5 | F4: =C4*(Supuestos!B27+Supuestos!B26*D4) -> 9.6112024 | G4: =Supuestos!B30*B4*(F4+Supuestos!B29) -> 2096.4663 | H4: =Supuestos!B17*Supuestos!B18*E4 -> 2880 | I4: =G4+H4 -> 4976.4663 | J4: =(I4-Costos!B17)/Costos!B17 -> -0.67955787 | K4: =Costos!B17/I4*12 -> 37.448259
A5: Esperado | B5: 0.7 | C5: 0.6 | D5: 0.25 | E5: 0.7 | F5: =C5*(Supuestos!B27+Supuestos!B26*D5) -> 14.340524 | G5: =Supuestos!B30*B5*(F5+Supuestos!B29) -> 3352.9613 | H5: =Supuestos!B17*Supuestos!B18*E5 -> 4032 | I5: =G5+H5 -> 7384.9613 | J5: =(I5-Costos!B17)/Costos!B17 -> -0.52447126 | K5: =Costos!B17/I5*12 -> 25.235068
A6: Optimista | B6: 0.8 | C6: 0.85 | D6: 0.4 | E6: 0.9 | F6: =C6*(Supuestos!B27+Supuestos!B26*D6) -> 26.280791 | G6: =Supuestos!B30*B6*(F6+Supuestos!B29) -> 6449.2621 | H6: =Supuestos!B17*Supuestos!B18*E6 -> 5184 | I6: =G6+H6 -> 11633.262 | J6: =(I6-Costos!B17)/Costos!B17 -> -0.2509168 | K6: =Costos!B17/I6*12 -> 16.019582
A8: Interpretación | B8: Los escenarios mantienen los costos y modifican la eficacia y la adopción.
A9: Rentabilidad en el primer año | B9: El ROI de los tres escenarios sigue siendo negativo.
A10: Horizonte de 3 años | B10: El escenario optimista supera los costos a tres años. El esperado no.
A11: Recupero | B11: El cálculo simple no descuenta gastos futuros; el adicional sí.
A13: PLAZO COMPLETO (INCLUYE MANTENIMIENTO) | B13: Beneficio anual (USD) | C13: ROI a 3 años | D13: Recupero con mantenimiento (meses) | E13: Lectura
A14: =A4 -> Conservador | B14: =I4 -> 4976.4663 | C14: =(B14*3-(Costos!B15+Costos!C16*3))/(Costos!B15+Costos!C16*3) -> -0.4561239 | D14: =IF(B14>Costos!C16,Costos!B15/(B14-Costos!C16)*12,"No recupera") -> No recupera | E14: Se compara el ahorro neto de mantener el proyecto
A15: =A5 -> Esperado | B15: =I5 -> 7384.9613 | C15: =(B15*3-(Costos!B15+Costos!C16*3))/(Costos!B15+Costos!C16*3) -> -0.19290041 | D15: =IF(B15>Costos!C16,Costos!B15/(B15-Costos!C16)*12,"No recupera") -> 80.591664 | E15: Se compara el ahorro neto de mantener el proyecto
A16: =A6 -> Optimista | B16: =I6 -> 11633.262 | C16: =(B16*3-(Costos!B15+Costos!C16*3))/(Costos!B15+Costos!C16*3) -> 0.27139477 | D16: =IF(B16>Costos!C16,Costos!B15/(B16-Costos!C16)*12,"No recupera") -> 20.242322 | E16: Se compara el ahorro neto de mantener el proyecto

Sheet Validacion
A1: CASA ÓGA | RESULTADOS REALES DE VALIDACIÓN
A3: Método con 600 alertas mensuales | B3: Aciertos | C3: Falsas alertas | D3: Casos omitidos | E3: Casos sanos sin alerta | F3: Recall
A4: Regla basada en cobertura | B4: 448 | C4: 3152 | D4: 406 | E4: 34356 | F4: 0.52459016
A5: Regresión logística | B5: 571 | C5: 3029 | D5: 283 | E5: 34479 | F5: 0.66861827
A6: Gradient Boosting | B6: 585 | C6: 3015 | D6: 269 | E6: 34493 | F6: 0.68501171
A8: Estimación de valor neto, seis meses | B8: Beneficio (USD) | C8: Cálculo
A9: Valor Gradient Boosting | B9: =Supuestos!B21*(B6*Supuestos!B28-C6*Supuestos!B29) -> -756.68993 | C9: Aciertos corregidos menos falsas acciones, con adopción 70%
A10: Valor regla a igual cantidad de alertas | B10: =Supuestos!B21*(B4*Supuestos!B28-C4*Supuestos!B29) -> -2433.1706 | C10: Mismo esfuerzo, 600 alertas mensuales
A11: Diferencia, seis meses | B11: =B9-B10 -> 1676.4806 | C11: Se proyecta el doble para un año
A12: Mejora anual proyectada | B12: =B11*2 -> 3352.9613 | C12: La diferencia de seis meses multiplicada por dos
A14: COMPARACIÓN CON LA REGLA FIJA ORIGINAL (SIN CUPO MENSUAL)
A15: Método | B15: Aciertos | C15: Falsas alertas | D15: Casos omitidos | E15: Casos sanos sin alerta | F15: Recall
A16: Regla fija: cobertura >12 meses (175 alertas/mes) | B16: 258 | C16: 792 | D16: 596 | E16: 36716 | F16: =B16/(B16+D16) -> 0.30210773
A18: Valor neto regla fija original (6 meses) | B18: =Supuestos!B21*(B16*Supuestos!B28-C16*Supuestos!B29) -> 848.51407
A19: Diferencia: modelo con 600 alertas menos regla fija | B19: =B9-B18 -> -1605.204
A21: Nota: la regla fija genera unas 175 alertas por mes. Su valor económico NO es comparable bajo el mismo esfuerzo con las 600 alertas mensuales de los otros métodos.

Sheet Sensibilidad
A1: CASA ÓGA | SENSIBILIDAD A LOS COSTOS REVISADOS
A3: Cambio respecto de base | B3: Valor modificado | C3: Beneficio anual (USD) | D3: ROI año 1
A4: Base | B4: Sin cambios | C4: =Supuestos!B33 -> 7384.9613 | D4: =(C4-Costos!B17)/Costos!B17 -> -0.52447126
A5: Adopción de alertas | B5: 70% → 60% | C5: =Supuestos!B31+Supuestos!B32*60/70 -> 6905.9668 | D5: =(C5-Costos!B17)/Costos!B17 -> -0.55531444
A6: Beneficio por acción acertada | B6: USD 14,34 → USD 7,17 | C6: =Supuestos!B33-Supuestos!B30*Supuestos!B21*(Supuestos!B28*0.5) -> 6009.705 | D6: =(C6-Costos!B17)/Costos!B17 -> -0.61302608
A7: Aciertos adicionales del modelo | B7: 137 → 96 en seis meses | C7: =Supuestos!B31+Supuestos!B32*96/137 -> 6381.5203 | D7: =(C7-Costos!B17)/Costos!B17 -> -0.58908433
A8: Mayor costo de preparación | B8: USD 1.000 → USD 2.000 | C8: =Supuestos!B33 -> 7384.9613 | D8: =(C8-(Costos!B17+1100))/(Costos!B17+1100) -> -0.55592536
A9: Menos tiempo manual ahorrado | B9: 70% → 35% | C9: =Supuestos!B32+Supuestos!B31/2 -> 5368.9613 | D9: =(C9-Costos!B17)/Costos!B17 -> -0.65428453
A10: Beneficio total se reduce a la mitad | B10: USD 7.385 → USD 3.692 | C10: =Supuestos!B33*0.5 -> 3692.4806 | D10: =(C10-Costos!B17)/Costos!B17 -> -0.76223563
A12: Criterio | B12: Cada fila cambia una condición y mantiene las otras como en el escenario esperado.
A13: Limitación | B13: El ahorro de horas es potencial: debe traducirse en costos efectivamente evitados.
A15: ROI a tres años si los beneficios se reducen a la mitad | B15: USD 7.385 → USD 3.692/año | C15: =C10 -> 3692.4806 | D15: =(3*C15-(Costos!B15+3*Costos!C16))/(Costos!B15+3*Costos!C16) -> -0.5964502

Sheet Actualizacion_Etapa4
A1: CASA ÓGA | ACTUALIZACIÓN DEL ROI CON LA ETAPA 4 (ESCENARIO ESPERADO)
A3: Concepto | B3: Parte B (Etapa 2, validación) | C3: Etapa 4 · validación 2025 | D3: Etapa 4 · test 2026 | E3: Valor en etapa4_resultados.json (val / test)
A4: Aciertos adicionales del modelo frente a la regla Top-600 (en el período) | B4: 137 | C4: 158 | D4: 177 | E4: 158 / 177
A5: Meses del período | B5: 6 | C5: 6 | D5: 5 | E5: 6 / 5
A6: Aciertos adicionales anualizados | B6: =B4/B5*12 -> 274 | C6: =C4/C5*12 -> 316 | D6: =D4/D5*12 -> 424.8 | E6: 316,0 / 424,8
A7: Valor por acierto adicional (USD) = 70% × (14,34 + 3,14) | B7: 12.237085 | C7: 12.237085 | D7: 12.237085 | E7: Parte B 3.3
A8: Beneficio predictivo anual (USD) | B8: =B6*B7 -> 3352.9613 | C8: =C6*C7 -> 3866.9188 | D8: =D6*D7 -> 5198.3137 | E8: 3867 / 5198
A9: Beneficio por horas ahorradas (USD) = 480 h × USD 12 × 70% | B9: 4032 | C9: 4032 | D9: 4032 | E9: Parte B 3.3
A10: Beneficio anual total (USD) | B10: =B8+B9 -> 7384.9613 | C10: =C8+C9 -> 7898.9188 | D10: =D8+D9 -> 9230.3137 | E10: 7899 / 9230
A11: Inversión inicial (USD) | B11: 9570 | C11: 9570 | D11: 9570 | E11: Parte B 3.2
A12: Mantenimiento anual (USD) | B12: 5960 | C12: 5960 | D12: 5960 | E12: Parte B 3.2
A13: ROI año 1 = (beneficio − inversión − mantenimiento) / (inversión + mantenimiento) | B13: =(B10-B11-B12)/(B11+B12) -> -0.52447126 | C13: =(C10-C11-C12)/(C11+C12) -> -0.49137677 | D13: =(D10-D11-D12)/(D11+D12) -> -0.40564625 | E13: -49,1% / -40,6%
A14: ROI a 3 años = (3 × beneficio − inversión − 3 × mantenimiento) / (inversión + 3 × mantenimiento) | B14: =(3*B10-B11-3*B12)/(B11+3*B12) -> -0.19290041 | C14: =(3*C10-C11-3*C12)/(C11+3*C12) -> -0.13673018 | D14: =(3*D10-D11-3*D12)/(D11+3*D12) -> 0.0087774513 | E14: -13,7% / 0,9%
A15: Recupero con mantenimiento (meses) = inversión / (beneficio − mantenimiento) × 12 | B15: =B11/(B10-B12)*12 -> 80.591664 | C15: =C11/(C10-C12)*12 -> 59.228885 | D15: =D11/(D10-D12)*12 -> 35.115898 | E15: 59,2 / 35,1
A17: Desempeño con 600 alertas por mes (Etapa 4)
A18: Indicador | B18: Validación 2025 (abr-sep) | C18: Test 2026 (ene-may)
A19: Positivos reales | B19: 854 | C19: 2535
A20: Prevalencia | B20: 0.022261613 | C20: 0.090309939
A21: VP ensamble Top-600 | B21: 606 | C21: 1950
A22: VP regla ordenada por cobertura Top-600 | B22: 448 | C22: 1773
A23: Recall@600 ensamble | B23: 0.70960187 | C23: 0.76923077
A24: Precisión@600 ensamble | B24: 0.16833333 | C24: 0.65
A25: Valor neto ensamble en el período (USD; VP × 10,04 − FP × 2,20) | B25: -502.56 | C25: 17268
A27: Fuente: Entregable 3/Modelo/resultados/etapa4_resultados.json (bloques "roi_escenario_esperado" y "periodos"), generado por Modelo/etapa4_evaluacion_final.py. Ver Secciones 8.1, 8.2 y 11.2 del documento compilado.
A28: Se mantienen todos los supuestos del escenario esperado de la Parte B (70% de adopción, 70% de horas ahorradas, USD 14,34 por acierto, USD 3,14 de costo evitado, inversión USD 9.570 y mantenimiento USD 5.960/año). Sólo cambian los aciertos adicionales frente a la regla con el mismo cupo de alertas.
A29: Se informa como rango: el test 2026 es un año más fácil (prevalencia 9,0% contra 2,2%) y proviene de un nuevo reporte consolidado.
A30: Las hojas originales de la Parte B (Costos, Supuestos, Escenarios, Validacion, Sensibilidad) no se modificaron.
